focused/__init__.py
focused/blocks.py
focused/focused.py
focused-1.1.3.dist-info/LICENSE
focused-1.1.3.dist-info/METADATA
focused-1.1.3.dist-info/WHEEL
focused-1.1.3.dist-info/top_level.txt
focused-1.1.3.dist-info/RECORD
