Metadata-Version: 2.1
Name: focused
Version: 1.1.3
Summary: Focused is a Python library that removes clutter from
Home-page: https://github.com/Imperator26/focused
Author: Federico A. Corazza
Author-email: federico.corazza@live.it
License: UNKNOWN
Platform: UNKNOWN
Classifier: Programming Language :: Python :: 3
Classifier: License :: OSI Approved :: MIT License
Classifier: Operating System :: OS Independent
Requires-Python: >=3.6
Requires-Dist: click (==7.0)
Requires-Dist: tqdm (==4.34.0)
Requires-Dist: requests (==2.22.0)
